bigt/__init__.py
bigt/dictext.py
bigt/pprint.py
tests/__init__.py
tests/test_dictext.py
tests/test_equel.py
tests/test_merge.py
tests/test_sort.py
Bigt-2022.1.4.dist-info/LICENSE
Bigt-2022.1.4.dist-info/METADATA
Bigt-2022.1.4.dist-info/WHEEL
Bigt-2022.1.4.dist-info/top_level.txt
Bigt-2022.1.4.dist-info/RECORD
