Metadata-Version: 2.1
Name: Bigt
Version: 2022.1.4
Summary: Bigt is a Python library for compare or merge nested unsorted dictionaries.
Home-page: https://gitlab.com/vladku/bigt
Author: Vladyslav Kurovskyi
Classifier: Programming Language :: Python :: 3
Classifier: License :: OSI Approved :: MIT License
Classifier: Operating System :: OS Independent
Classifier: Intended Audience :: Developers
License-File: LICENSE
Provides-Extra: rich
Requires-Dist: rich ; extra == 'rich'
